README.rst
setup.py
thermocouples_reference/__init__.py
thermocouples_reference/function_types.py
thermocouples_reference/source_ASTM.py
thermocouples_reference/source_NIST.py
thermocouples_reference/source_OMEGA.py
thermocouples_reference/units.py
thermocouples_reference.egg-info/PKG-INFO
thermocouples_reference.egg-info/SOURCES.txt
thermocouples_reference.egg-info/dependency_links.txt
thermocouples_reference.egg-info/requires.txt
thermocouples_reference.egg-info/top_level.txt
thermocouples_reference.egg-info/zip-safe