Metadata-Version: 1.1
Name: thermocouples-reference
Version: 0.20
Summary: Thermocouple emf reference functions
Home-page: https://pypi.python.org/pypi/thermocouples_reference
Author: User:Nanite @ wikipedia
Author-email: UNKNOWN
License: public domain
Keywords: thermocouple,thermometer,temperature,emf,electromotive,thermoelectric,Seebeck,lookup,table,NIST,ASTM
Platform: UNKNOWN
Classifier: Development Status :: 4 - Beta
Classifier: Intended Audience :: Science/Research
Classifier: Intended Audience :: Manufacturing
Classifier: Topic :: Scientific/Engineering :: Physics
Classifier: License :: Public Domain
Classifier: Operating System :: OS Independent
Classifier: Programming Language :: Python
